episode_dl/__init__.py
episode_dl/feed.py
Episode_DL-2020.5.4.dist-info/METADATA
Episode_DL-2020.5.4.dist-info/WHEEL
Episode_DL-2020.5.4.dist-info/top_level.txt
Episode_DL-2020.5.4.dist-info/RECORD
