Metadata-Version: 2.1
Name: Episode-DL
Version: 2020.5.4
Summary: (Podcast-)Episode)-D(own)L(oader). Download Podcast Episodes with Ease
Home-page: https://github.com/kjaymiller/episode_dl
Author: Jay Miller
Author-email: kjaymiller@gmail.com
License: MIT
Platform: UNKNOWN
Requires-Dist: feedparser
Requires-Dist: requests
